vbpdf/__init__.py
vbpdf/__main__.py
vbpdf/addbg.py
vbpdf/blur.py
vbpdf/choice_option.py
vbpdf/functions_pdf.py
vbpdf/instagram.py
vbpdf/main.py
vbpdf/overlay.py
vbpdf/split.py
vbpdf/stack.py
vbpdf/topng.py
vbpdf/webpage.py
vbpdf-0.1.50.dist-info/METADATA
vbpdf-0.1.50.dist-info/WHEEL
vbpdf-0.1.50.dist-info/entry_points.txt
vbpdf-0.1.50.dist-info/RECORD
