Metadata-Version: 2.1
Name: vbpdf
Version: 0.1.50
Summary: There was this issue with single page pdf in instagram stacking and blurring _ i fixed that.
Home-page: https://github.com/vaibhavblayer/vbpdf
Keywords: split pdf,annotate pdf,pdftopng,png,pdf
Author: vaibhavblayer
Author-email: vaibhavblayer@gmail.com
Requires-Python: >=3.11,<4.0
Classifier: Programming Language :: Python :: 3
Classifier: Programming Language :: Python :: 3.11
Classifier: Programming Language :: Python :: 3.12
Requires-Dist: click (>=8.1.3,<9.0.0)
Project-URL: Repository, https://github.com/vaibhavblayer/vbpdf
